NameGenderPredictor/NameGenderPredictor.py
NameGenderPredictor/__init__.py
NameGenderPredictor/nameGenderUSSSA.db
NameGenderPredictor-0.0.1.dist-info/LICENSE
NameGenderPredictor-0.0.1.dist-info/METADATA
NameGenderPredictor-0.0.1.dist-info/WHEEL
NameGenderPredictor-0.0.1.dist-info/top_level.txt
NameGenderPredictor-0.0.1.dist-info/RECORD
