Metadata-Version: 2.1
Name: NameGenderPredictor
Version: 0.0.1
Summary: Prediction of gender probabilities for English names.
Home-page: https://github.com/xiaoha798/py-NameGenderPredictor
Author: Hadrien Van Lierde
Author-email: hadrien.vanlierde@gmail.com
License: UNKNOWN
Platform: UNKNOWN
Classifier: Programming Language :: Python :: 3
Classifier: License :: OSI Approved :: MIT License
Classifier: Operating System :: OS Independent
Requires-Python: >=3.7
